clixify/__init__.py
clixify/base.py
clixify/client.py
clixify/folder.py
clixify/list.py
clixify/space.py
clixify/task.py
clixify/team.py
clixify/utils/__init__.py
clixify/utils/exceptions.py
clixify-0.1.4.dist-info/METADATA
clixify-0.1.4.dist-info/WHEEL
clixify-0.1.4.dist-info/top_level.txt
clixify-0.1.4.dist-info/RECORD
