Metadata-Version: 2.4
Name: clixify
Version: 0.1.4
Summary: Clixify: Python Client for ClickUp API v2
Author-email: Mohammed Shaawa <mshaawa963@gmail.com>
License: MIT
Requires-Python: >=3.8
Requires-Dist: certifi==2025.1.31
Requires-Dist: charset-normalizer==3.4.1
Requires-Dist: idna==3.10
Requires-Dist: python-dotenv==1.1.0
Requires-Dist: requests==2.32.3
Requires-Dist: urllib3==2.4.0
